[{"code":"370282004001","name":"新都居委会"},{"code":"370282004002","name":"太和路社区居民委员会"},{"code":"370282004200","name":"营东村委会"},{"code":"370282004201","name":"营西村委会"},{"code":"370282004202","name":"朱家后戈庄村委会"},{"code":"370282004203","name":"王家后戈庄村委会"},{"code":"370282004204","name":"刘家后戈庄村委会"},{"code":"370282004205","name":"郭家庄村委会"},{"code":"370282004206","name":"秦家庄村委会"},{"code":"370282004207","name":"兰家庄村委会"},{"code":"370282004208","name":"曹家庄村委会"},{"code":"370282004209","name":"胡家庄村委会"},{"code":"370282004210","name":"上疃村委会"},{"code":"370282004211","name":"和尚庄村委会"},{"code":"370282004212","name":"南林戈庄村委会"},{"code":"370282004213","name":"北林戈庄村委会"},{"code":"370282004214","name":"肖家疃村委会"},{"code":"370282004215","name":"程家疃村委会"},{"code":"370282004216","name":"邹家疃村委会"},{"code":"370282004217","name":"谭家疃村委会"},{"code":"370282004218","name":"姜吉庄村委会"},{"code":"370282004219","name":"小庄村委会"},{"code":"370282004220","name":"下疃村委会"},{"code":"370282004221","name":"宋化泉村委会"},{"code":"370282004222","name":"瓜娄屯村委会"},{"code":"370282004223","name":"双龙埠村委会"},{"code":"370282004224","name":"南龙埠村委会"},{"code":"370282004225","name":"前王宿庄村委会"},{"code":"370282004226","name":"后王宿庄村委会"},{"code":"370282004227","name":"北龙堂埠村委会"},{"code":"370282004228","name":"辛庄一村委会"},{"code":"370282004229","name":"辛庄二村委会"},{"code":"370282004230","name":"辛庄三村委会"},{"code":"370282004231","name":"郑家庄村委会"},{"code":"370282004232","name":"泉岭村委会"},{"code":"370282004233","name":"泥洼村委会"},{"code":"370282004242","name":"凤凰庄村村委会"},{"code":"370282004243","name":"三官庙村村委会"},{"code":"370282004244","name":"玉皇庙村村委会"},{"code":"370282004245","name":"侯东村村委会"},{"code":"370282004246","name":"侯西村村委会"},{"code":"370282004247","name":"李家疃村村委会"},{"code":"370282004248","name":"隋家疃村村委会"},{"code":"370282004249","name":"兰东村村委会"},{"code":"370282004250","name":"院上村村委会"},{"code":"370282004251","name":"方戈庄村村委会"},{"code":"370282004252","name":"蒲洼村村委会"},{"code":"370282004253","name":"西北岭村村委会"},{"code":"370282004254","name":"大北岭村村委会"},{"code":"370282004255","name":"李家岭村村委会"},{"code":"370282004256","name":"周集村村委会"},{"code":"370282004257","name":"周北村村委会"},{"code":"370282004258","name":"兰家庄村村委会"},{"code":"370282004259","name":"卢家庄村村委会"},{"code":"370282004260","name":"周南村村委会"},{"code":"370282004261","name":"杨家演泉村委会"},{"code":"370282004262","name":"何家演泉村委会"},{"code":"370282004263","name":"刘家演泉村委会"},{"code":"370282004264","name":"吕家演泉村委会"}]