[{"code":"370282006200","name":"范家街村委会"},{"code":"370282006201","name":"河东杨头村委会"},{"code":"370282006202","name":"河北杨头村委会"},{"code":"370282006203","name":"韩家后寨村委会"},{"code":"370282006204","name":"东蒋戈庄村委会"},{"code":"370282006205","name":"西蒋戈庄村委会"},{"code":"370282006206","name":"张家小庄村委会"},{"code":"370282006207","name":"河南崖村委会"},{"code":"370282006208","name":"修家街村委会"},{"code":"370282006209","name":"潘家泊村委会"},{"code":"370282006210","name":"北窝洛子村委会"},{"code":"370282006211","name":"单家街村委会"},{"code":"370282006212","name":"李家街村委会"},{"code":"370282006213","name":"刘家街村委会"},{"code":"370282006214","name":"高家屯村委会"},{"code":"370282006215","name":"邵家屯村委会"},{"code":"370282006216","name":"俞家屯村委会"},{"code":"370282006217","name":"汪汪泊村委会"},{"code":"370282006218","name":"小王家庄村委会"},{"code":"370282006219","name":"于家兰蒿埠村委会"},{"code":"370282006220","name":"崔家兰蒿埠村委会"},{"code":"370282006221","name":"钟家兰蒿埠村委会"},{"code":"370282006222","name":"何家庄村委会"},{"code":"370282006223","name":"石泉头后村委会"},{"code":"370282006224","name":"石泉头前村委会"},{"code":"370282006225","name":"小寨村委会"},{"code":"370282006226","name":"大寨村委会"},{"code":"370282006227","name":"柳林村委会"},{"code":"370282006228","name":"玉石头村委会"},{"code":"370282006233","name":"石门村村委会"},{"code":"370282006234","name":"东塔子夼村村委会"},{"code":"370282006235","name":"西塔子夼村村委会"},{"code":"370282006236","name":"前麦泊村村委会"},{"code":"370282006237","name":"后麦泊村村委会"},{"code":"370282006238","name":"黄甲山村村委会"},{"code":"370282006239","name":"窑上村村委会"},{"code":"370282006240","name":"解家村村委会"},{"code":"370282006241","name":"大埠村村委会"},{"code":"370282006242","name":"小埠村村委会"},{"code":"370282006243","name":"辛疃村村委会"},{"code":"370282006244","name":"笏立头村村委会"},{"code":"370282006245","name":"果元村村委会"},{"code":"370282006246","name":"岭上村村委会"},{"code":"370282006247","name":"汪河水南村村委会"},{"code":"370282006248","name":"汪河水北村村委会"},{"code":"370282006249","name":"前碾子头村村委会"},{"code":"370282006250","name":"后碾子头村村委会"},{"code":"370282006251","name":"满贡一村村委会"},{"code":"370282006252","name":"满贡二村村委会"},{"code":"370282006253","name":"满贡三村村委会"},{"code":"370282006254","name":"吴家庄村村委会"},{"code":"370282006255","name":"解戈庄村村委会"},{"code":"370282006256","name":"东河北村村委会"},{"code":"370282006257","name":"西河北村村委会"},{"code":"370282006258","name":"李家蒲渠村村委会"},{"code":"370282006259","name":"台子村村委会"},{"code":"370282006260","name":"邹家蒲渠村村委会"},{"code":"370282006261","name":"张家庄村村委会"},{"code":"370282006262","name":"前蒲渠店村村委会"},{"code":"370282006263","name":"后蒲渠店村村委会"},{"code":"370282006264","name":"梁家屯村村委会"}]