[{"code":"370211103200","name":"泊里河东村委会"},{"code":"370211103201","name":"泊里河西村委会"},{"code":"370211103202","name":"泊里河南村委会"},{"code":"370211103203","name":"泊里河北村委会"},{"code":"370211103204","name":"孙家庄村委会"},{"code":"370211103205","name":"张家庄村委会"},{"code":"370211103206","name":"高家庄村委会"},{"code":"370211103207","name":"马家庄村委会"},{"code":"370211103208","name":"董辛庄村委会"},{"code":"370211103209","name":"董家小庄村委会"},{"code":"370211103210","name":"尹家村村委会"},{"code":"370211103211","name":"三合村村委会"},{"code":"370211103212","name":"石岭村委会"},{"code":"370211103213","name":"崔家村委会"},{"code":"370211103214","name":"邱家庄村委会"},{"code":"370211103215","name":"蒋家庄村委会"},{"code":"370211103216","name":"程家庄村委会"},{"code":"370211103217","name":"魏家村村委会"},{"code":"370211103218","name":"前松园村委会"},{"code":"370211103219","name":"后松园村委会"},{"code":"370211103220","name":"磊石村委会"},{"code":"370211103221","name":"米家庄村委会"},{"code":"370211103222","name":"东封家村村委会"},{"code":"370211103223","name":"河西村村委会"},{"code":"370211103224","name":"西封家村村委会"},{"code":"370211103225","name":"周村村委会"},{"code":"370211103226","name":"丁莪家庄村委会"},{"code":"370211103227","name":"蟠龙庵村委会"},{"code":"370211103228","name":"李家庄村委会"},{"code":"370211103229","name":"东小滩村委会"},{"code":"370211103230","name":"西小滩村委会"},{"code":"370211103231","name":"封家官庄村委会"},{"code":"370211103232","name":"贡口村委会"},{"code":"370211103233","name":"尹家圈村委会"},{"code":"370211103234","name":"东红石村委会"},{"code":"370211103235","name":"西红石村委会"},{"code":"370211103236","name":"前红石村委会"},{"code":"370211103237","name":"子良山后村委会"},{"code":"370211103238","name":"吕家庄村委会"},{"code":"370211103239","name":"营东头村委会"},{"code":"370211103240","name":"长松庄村委会"},{"code":"370211103241","name":"管家庄村委会"},{"code":"370211103242","name":"代家村村委会"},{"code":"370211103243","name":"常河店村委会"},{"code":"370211103244","name":"麦墩村委会"},{"code":"370211103245","name":"魏家滩村委会"},{"code":"370211103246","name":"口上村委会"},{"code":"370211103247","name":"肖家贡村委会"},{"code":"370211103248","name":"黄家庄村委会"},{"code":"370211103249","name":"董大庄村委会"},{"code":"370211103250","name":"营上村村委会"},{"code":"370211103251","name":"小庄村委会"},{"code":"370211103252","name":"丰台村村委会"},{"code":"370211103253","name":"棋子湾村委会"},{"code":"370211103254","name":"撒牛沟村委会"},{"code":"370211103255","name":"尧头一村村委会"},{"code":"370211103256","name":"尧头二村村委会"},{"code":"370211103257","name":"尧头三村村委会"},{"code":"370211103258","name":"尧头四村村委会"},{"code":"370211103259","name":"沐官岛村委会"},{"code":"370211103260","name":"朱家河村委会"},{"code":"370211103261","name":"草桥村委会"},{"code":"370211103262","name":"封家庄村委会"},{"code":"370211103263","name":"崔家疃子村委会"},{"code":"370211103264","name":"季家村村委会"},{"code":"370211103265","name":"小刘家庄村委会"},{"code":"370211103266","name":"小王家村村委会"},{"code":"370211103267","name":"小塔山村委会"},{"code":"370211103268","name":"信阳一村村委会"},{"code":"370211103269","name":"信阳二村村委会"},{"code":"370211103270","name":"信阳三村村委会"},{"code":"370211103271","name":"柳树底村委会"},{"code":"370211103272","name":"沙岭子村委会"},{"code":"370211103273","name":"小滩村委会"},{"code":"370211103274","name":"石崖村委会"},{"code":"370211103275","name":"岭前头村委会"},{"code":"370211103276","name":"东庄村委会"},{"code":"370211103277","name":"西庄村委会"},{"code":"370211103278","name":"南庄村委会"},{"code":"370211103279","name":"湾崖村委会"},{"code":"370211103280","name":"庙东村委会"},{"code":"370211103281","name":"庙后村委会"},{"code":"370211103282","name":"崖下上庄村委会"},{"code":"370211103283","name":"徐家官庄村委会"},{"code":"370211103284","name":"菜园村委会"},{"code":"370211103285","name":"前草场村委会"},{"code":"370211103286","name":"后草场村委会"},{"code":"370211103287","name":"营里村委会"},{"code":"370211103288","name":"旺山村委会"},{"code":"370211103289","name":"大溜村委会"},{"code":"370211103290","name":"小溜村委会"},{"code":"370211103291","name":"王家岭村委会"},{"code":"370211103292","name":"朱家庄村委会"},{"code":"370211103293","name":"海岱庄村委会"},{"code":"370211103294","name":"甲滩村委会"},{"code":"370211103295","name":"耿家岚村委会"},{"code":"370211103296","name":"邵家岚村委会"},{"code":"370211103297","name":"苗家岭村委会"},{"code":"370211103298","name":"大岚村委会"},{"code":"370211103299","name":"岚庙后村委会"},{"code":"370211103300","name":"后岚村委会"}]