[{"code":"370282121200","name":"西王村村委会"},{"code":"370282121201","name":"北王村村委会"},{"code":"370282121202","name":"中王村村委会"},{"code":"370282121203","name":"东王村村委会"},{"code":"370282121204","name":"南王村村委会"},{"code":"370282121205","name":"农林村村委会"},{"code":"370282121206","name":"南坦村村委会"},{"code":"370282121207","name":"北坦村村委会"},{"code":"370282121208","name":"西坦村村委会"},{"code":"370282121209","name":"闫家庄村委会"},{"code":"370282121210","name":"山口村委会"},{"code":"370282121211","name":"马山后村委会"},{"code":"370282121212","name":"小桥村委会"},{"code":"370282121213","name":"邓家埠村委会"},{"code":"370282121214","name":"杨戈庄村委会"},{"code":"370282121215","name":"小丈村委会"},{"code":"370282121216","name":"上古庄屯村委会"},{"code":"370282121217","name":"下古庄屯村委会"},{"code":"370282121218","name":"周家高戈庄村委会"},{"code":"370282121219","name":"朱家高戈庄村委会"},{"code":"370282121220","name":"马家高戈庄村委会"},{"code":"370282121221","name":"王家高戈庄村委会"},{"code":"370282121222","name":"迟家高戈庄村委会"},{"code":"370282121223","name":"谢家埠后村村委会"},{"code":"370282121224","name":"鲁家埠后村村委会"},{"code":"370282121225","name":"林家埠后村村委会"},{"code":"370282121226","name":"黄官屯村村委会"},{"code":"370282121227","name":"蒲湾头村委会"},{"code":"370282121228","name":"卧龙村委会"},{"code":"370282121229","name":"大桥村委会"},{"code":"370282121230","name":"抬头村委会"},{"code":"370282121231","name":"新安村委会"},{"code":"370282121232","name":"沙戈庄村委会"},{"code":"370282121233","name":"黑石庄村委会"},{"code":"370282121234","name":"黄庵村委会"},{"code":"370282121235","name":"洼里村委会"},{"code":"370282121236","name":"崔诏村委会"},{"code":"370282121237","name":"上夼村委会"},{"code":"370282121238","name":"江家屯村委会"},{"code":"370282121239","name":"宅科村委会"},{"code":"370282121240","name":"英里村委会"},{"code":"370282121241","name":"潘家村委会"},{"code":"370282121242","name":"迟家村委会"},{"code":"370282121243","name":"仲村村委会"},{"code":"370282121244","name":"沟里村委会"},{"code":"370282121245","name":"东辛庄村委会"},{"code":"370282121246","name":"泊子村委会"},{"code":"370282121247","name":"夼子村委会"},{"code":"370282121248","name":"宋家村委会"},{"code":"370282121249","name":"于家屯村委会"},{"code":"370282121250","name":"郑家村委会"},{"code":"370282121251","name":"房家村委会"},{"code":"370282121252","name":"周戈庄村委会"},{"code":"370282121253","name":"中韩家屯村委会"},{"code":"370282121254","name":"羊山后村委会"},{"code":"370282121255","name":"南韩家屯村委会"},{"code":"370282121256","name":"黄龙庄村委会"},{"code":"370282121257","name":"纪家庄村委会"},{"code":"370282121258","name":"东孟戈庄村委会"},{"code":"370282121259","name":"西孟戈庄村委会"},{"code":"370282121260","name":"埠西村委会"},{"code":"370282121261","name":"黑子村委会"},{"code":"370282121262","name":"大山前村委会"},{"code":"370282121263","name":"西崔戈庄村委会"},{"code":"370282121264","name":"东崔戈庄村委会"},{"code":"370282121265","name":"田横岛村村委会"},{"code":"370282121266","name":"东陆戈庄村村委会"},{"code":"370282121267","name":"西陆戈庄村村委会"},{"code":"370282121268","name":"山东头村村委会"},{"code":"370282121269","name":"何家寨村村委会"},{"code":"370282121270","name":"董家寨村村委会"},{"code":"370282121271","name":"李家寨村村委会"},{"code":"370282121272","name":"刘家寨村村委会"},{"code":"370282121273","name":"苏家寨村村委会"},{"code":"370282121274","name":"南营子村村委会"},{"code":"370282121275","name":"拖车口村村委会"},{"code":"370282121276","name":"现子埠村村委会"},{"code":"370282121277","name":"谗山村村委会"},{"code":"370282121278","name":"南谗山村村委会"},{"code":"370282121279","name":"山南村村委会"},{"code":"370282121280","name":"钓鱼嘴村村委会"},{"code":"370282121281","name":"南丁戈庄村村委会"},{"code":"370282121282","name":"北丁戈庄村村委会"},{"code":"370282121283","name":"任家丰城村委会"},{"code":"370282121284","name":"时家丰城村委会"},{"code":"370282121285","name":"于家丰城村委会"},{"code":"370282121286","name":"丰城河南村委会"},{"code":"370282121287","name":"七口村委会"},{"code":"370282121288","name":"北颜武村委会"},{"code":"370282121289","name":"南颜武村委会"},{"code":"370282121290","name":"彭家屯村委会"},{"code":"370282121291","name":"刁家大丈村委会"},{"code":"370282121292","name":"宫家大丈村委会"},{"code":"370282121293","name":"八亩地村委会"},{"code":"370282121294","name":"上庄村委会"},{"code":"370282121295","name":"崔家沟村委会"},{"code":"370282121296","name":"王家屯村委会"},{"code":"370282121297","name":"芝坊村委会"},{"code":"370282121298","name":"马坊村委会"},{"code":"370282121299","name":"时家庄子村委会"},{"code":"370282121300","name":"河东村委会"},{"code":"370282121301","name":"河西村委会"},{"code":"370282121302","name":"南芦村委会"},{"code":"370282121303","name":"北芦村委会"},{"code":"370282121304","name":"北雄崖所村委会"},{"code":"370282121305","name":"南雄崖所村委会"},{"code":"370282121306","name":"王戈庄村委会"},{"code":"370282121307","name":"田庄村委会"},{"code":"370282121308","name":"东龙湾头村委会"},{"code":"370282121309","name":"前车家夼村委会"},{"code":"370282121310","name":"后车家夼村委会"},{"code":"370282121311","name":"苏口村委会"},{"code":"370282121312","name":"西百里村委会"},{"code":"370282121313","name":"东百里村委会"},{"code":"370282121314","name":"南百里村委会"},{"code":"370282121315","name":"福台岭村委会"},{"code":"370282121316","name":"营子村委会"},{"code":"370282121317","name":"泉子头村委会"},{"code":"370282121318","name":"韩家屯村委会"},{"code":"370282121319","name":"绿豆圈村委会"},{"code":"370282121320","name":"东村村委会"},{"code":"370282121321","name":"外栲栳村委会"},{"code":"370282121322","name":"里栲栳村委会"},{"code":"370282121323","name":"圈里村委会"},{"code":"370282121324","name":"杜家村委会"}]