[{"code":"370211007001","name":"塔山社区居民委员会"},{"code":"370211007002","name":"两河社区居民委员会"},{"code":"370211007003","name":"学院路社区居民委员会"},{"code":"370211007200","name":"东门外村委会"},{"code":"370211007201","name":"西街村委会"},{"code":"370211007202","name":"北门里村委会"},{"code":"370211007203","name":"南街村委会"},{"code":"370211007204","name":"东街村委会"},{"code":"370211007205","name":"郑戈庄村委会"},{"code":"370211007206","name":"赵家庙村委会"},{"code":"370211007207","name":"开山口村委会"},{"code":"370211007208","name":"大楼村委会"},{"code":"370211007209","name":"蔡家庄村委会"},{"code":"370211007210","name":"小洼村委会"},{"code":"370211007211","name":"白果树村委会"},{"code":"370211007212","name":"张家村村委会"},{"code":"370211007213","name":"毛家山村委会"},{"code":"370211007214","name":"西门外村委会"},{"code":"370211007215","name":"西南园村委会"},{"code":"370211007216","name":"北街村委会"},{"code":"370211007217","name":"北门外村委会"},{"code":"370211007218","name":"朱戈庄村委会"},{"code":"370211007219","name":"黄石圈村委会"},{"code":"370211007220","name":"西南村村委会"},{"code":"370211007221","name":"南门里村委会"},{"code":"370211007222","name":"大湾村委会"},{"code":"370211007223","name":"窝洛子村委会"},{"code":"370211007224","name":"北窑村委会"},{"code":"370211007225","name":"杨七岭村委会"},{"code":"370211007226","name":"山子西村委会"},{"code":"370211007227","name":"李家河村委会"},{"code":"370211007228","name":"东赵家村委会"},{"code":"370211007229","name":"积米崖村委会"},{"code":"370211007230","name":"大岔口村委会"},{"code":"370211007231","name":"城口子村委会"},{"code":"370211007232","name":"李家村村委会"},{"code":"370211007233","name":"毛家沟村委会"},{"code":"370211007234","name":"崮上村委会"},{"code":"370211007235","name":"东山冯村委会"},{"code":"370211007236","name":"西山冯村委会"},{"code":"370211007237","name":"东山村村委会"},{"code":"370211007238","name":"北山村村委会"},{"code":"370211007239","name":"陡崖子村委会"},{"code":"370211007240","name":"长城村村委会"},{"code":"370211007241","name":"卜落林村委会"},{"code":"370211007242","name":"赵家河村委会"},{"code":"370211007243","name":"东大洼村委会"},{"code":"370211007244","name":"东华山村委会"},{"code":"370211007245","name":"西华山村委会"},{"code":"370211007246","name":"蒋家窑村委会"},{"code":"370211007247","name":"店头村委会"},{"code":"370211007248","name":"前洼村委会"},{"code":"370211007249","name":"大兰东村委会"},{"code":"370211007250","name":"小兰东村委会"},{"code":"370211007251","name":"北高家庄村委会"},{"code":"370211007252","name":"林家庄村委会"},{"code":"370211007253","name":"蒋家店子村委会"},{"code":"370211007254","name":"三家庄村委会"},{"code":"370211007255","name":"山前村委会"},{"code":"370211007256","name":"新建村委会"},{"code":"370211007257","name":"辛屯村委会"},{"code":"370211007258","name":"两河村委会"}]